Metadata-Version: 2.1
Name: libpython-marqueane
Version: 0.1
Summary: Exemplo de construção de projetos Python - Curso Pytools
Home-page: https://github.com/MarqueaneSouza/libpythonpytools
Author: Marqueane Carvalho
Author-email: marqueane_64@hotmail.com
License: GNU AFFERO GENERAL PUBLIC LICENSE
Platform: UNKNOWN
Classifier: Development Status :: 2 - Pre-Alpha
Classifier: Environment :: Console
Classifier: Intended Audience :: Developers
Classifier: License :: OSI Approved :: GNU Affero General Public License v3 or later (AGPLv3+)
Classifier: Operating System :: OS Independent
Classifier: Programming Language :: Python
Classifier: Programming Language :: Python :: 3.10
Classifier: Framework :: Pytest
License-File: LICENSE
